pyocr/__init__.py
pyocr/_version.py
pyocr/builders.py
pyocr/cuneiform.py
pyocr/error.py
pyocr/pyocr.py
pyocr/tesseract.py
pyocr/util.py
pyocr/libtesseract/__init__.py
pyocr/libtesseract/tesseract_raw.py
pyocr-0.8.5.dist-info/AUTHORS
pyocr-0.8.5.dist-info/COPYING
pyocr-0.8.5.dist-info/METADATA
pyocr-0.8.5.dist-info/WHEEL
pyocr-0.8.5.dist-info/top_level.txt
pyocr-0.8.5.dist-info/RECORD
