Metadata-Version: 2.1
Name: pyocr
Version: 0.8.5
Summary: A Python wrapper for OCR engines (Tesseract, Cuneiform, etc)
Author-email: Jerome Flesch <jflesch@openpaper.work>
License: GPL-3.0-or-later
License-File: COPYING
License-File: AUTHORS
Requires-Dist: Pillow
Provides-Extra: dev
Requires-Dist: pytest; extra == "dev"
Provides-Extra: lint
Requires-Dist: flake8; extra == "lint"
